pyrosimple/__init__.py
pyrosimple/config.py
pyrosimple/data/__init__.py
pyrosimple/data/full-example.rc
pyrosimple/error.py
pyrosimple/io/__init__.py
pyrosimple/io/scgi.py
pyrosimple/job/__init__.py
pyrosimple/job/action.py
pyrosimple/job/base.py
pyrosimple/job/metrics.py
pyrosimple/job/move_path.py
pyrosimple/job/move_torrent.py
pyrosimple/job/queue.py
pyrosimple/job/watch.py
pyrosimple/py.typed
pyrosimple/scripts/__init__.py
pyrosimple/scripts/base.py
pyrosimple/scripts/chtor.py
pyrosimple/scripts/lstor.py
pyrosimple/scripts/mktor.py
pyrosimple/scripts/pyroadmin.py
pyrosimple/scripts/pyrotorque.py
pyrosimple/scripts/rtcontrol.py
pyrosimple/scripts/rtmv_legacy.py
pyrosimple/scripts/rtxmlrpc.py
pyrosimple/torrent/__init__.py
pyrosimple/torrent/engine.py
pyrosimple/torrent/rtorrent.py
pyrosimple/ui/__init__.py
pyrosimple/ui/categories.py
pyrosimple/util/__init__.py
pyrosimple/util/cache.py
pyrosimple/util/fmt.py
pyrosimple/util/matching.py
pyrosimple/util/metafile.py
pyrosimple/util/pymagic.py
pyrosimple/util/rpc.py
pyrosimple/util/traits.py
pyrosimple/util/ui.py
pyrosimple-2.14.2.dist-info/COPYING
pyrosimple-2.14.2.dist-info/METADATA
pyrosimple-2.14.2.dist-info/WHEEL
pyrosimple-2.14.2.dist-info/entry_points.txt
pyrosimple-2.14.2.dist-info/RECORD
