Metadata-Version: 2.1
Name: pyrosimple
Version: 2.14.2
Summary: A stripped-down version of the pyrocore tools for working with rTorrent
Home-page: https://github.com/kannibalox/pyrosimple
License: GPL-3.0-or-later
Author: kannibalox
Author-email: kannibalox@gmail.com
Requires-Python: >=3.7.2,<4
Classifier: Development Status :: 4 - Beta
Classifier: Environment :: Console
Classifier: License :: OSI Approved :: GNU General Public License v3 or later (GPLv3+)
Classifier: Natural Language :: English
Classifier: Operating System :: POSIX
Classifier: Programming Language :: Python :: 3
Classifier: Programming Language :: Python :: 3.8
Classifier: Programming Language :: Python :: 3.9
Classifier: Programming Language :: Python :: 3.10
Classifier: Programming Language :: Python :: 3.11
Classifier: Programming Language :: Python :: 3.12
Classifier: Programming Language :: Python :: 3.13
Classifier: Programming Language :: Python :: 3 :: Only
Classifier: Programming Language :: Python :: 3.7
Classifier: Topic :: Communications :: File Sharing
Classifier: Topic :: Software Development :: Libraries :: Python Modules
Classifier: Topic :: Utilities
Provides-Extra: torque
Requires-Dist: APScheduler (>=3.9.0,<4.0.0) ; extra == "torque"
Requires-Dist: Jinja2 (>=3.1.0,<4.0.0)
Requires-Dist: bencode.py (>=4.0.0,<5.0.0)
Requires-Dist: importlib-metadata (==6.7.0) ; python_version == "3.7"
Requires-Dist: importlib-resources (>=5.4.0,<6.0.0) ; python_version < "3.9"
Requires-Dist: inotify (>=0.2.10,<0.3.0) ; extra == "torque"
Requires-Dist: parsimonious (>=0.10.0,<0.11.0)
Requires-Dist: prometheus-client (>=0.16.0,<0.17.0)
Requires-Dist: prompt-toolkit (>=3.0.30,<4.0.0)
Requires-Dist: python-box (>=7.0.0,<8.0.0)
Requires-Dist: python-daemon (>=3.0.1,<4.0.0)
Requires-Dist: requests (>=2.28.1,<3.0.0)
Requires-Dist: shtab (>=1.5.5,<2.0.0)
Requires-Dist: tomli (>=2.0.1,<3.0.0) ; python_version < "3.11"
Requires-Dist: tomli-w (>=1.0.0,<2.0.0)
Project-URL: Documentation, https://kannibalox.github.io/pyrosimple/
Project-URL: Repository, https://github.com/kannibalox/pyrosimple
